CLASSIFIERS
HISTORY.rst
LICENSE.txt
MANIFEST.in
README.rst
setup.cfg
setup.py
versioneer.py
OAS3.egg-info/PKG-INFO
OAS3.egg-info/SOURCES.txt
OAS3.egg-info/dependency_links.txt
OAS3.egg-info/not-zip-safe
OAS3.egg-info/requires.txt
OAS3.egg-info/top_level.txt
doc/Makefile
doc/source/.DS_Store
doc/source/conf.py
doc/source/index.rst
doc/source/_static/limiter.css
doc/source/_static/logo.png
doc/source/_static/small-logo.png
doc/source/_static/tap-icon.png
doc/source/_static/tap-logo.png
doc/source/_templates/sidebarintro.html
oas3/__init__.py
oas3/_version.py
oas3/base.py
oas3/errors.py
oas3/primitives.py
oas3/util.py
oas3/version.py
oas3.egg-info/PKG-INFO
oas3.egg-info/SOURCES.txt
oas3.egg-info/dependency_links.txt
oas3.egg-info/not-zip-safe
oas3.egg-info/requires.txt
oas3.egg-info/top_level.txt
oas3/objects/__init__.py
oas3/objects/external_docs.py
oas3/objects/info.py
oas3/objects/server.py
oas3/objects/tag.py
oas3/objects/components/__init__.py
oas3/objects/components/callback.py
oas3/objects/components/encoding.py
oas3/objects/components/example.py
oas3/objects/components/header.py
oas3/objects/components/link.py
oas3/objects/components/media_type.py
oas3/objects/components/parameter.py
oas3/objects/components/request_body.py
oas3/objects/components/response.py
oas3/objects/components/schema.py
oas3/objects/components/security_scheme.py
oas3/objects/path/__init__.py
oas3/objects/path/operation.py
requirements/ci.txt
requirements/dev.txt
requirements/doc.txt
requirements/main.txt
requirements/test.txt