Metadata-Version: 1.1
Name: oas3
Version: 0.1.13
Summary: A library for dealing with OpenAPI v3 specifications in Python
Home-page: https://oas3.readthedocs.org
Author: Pinn Technologies, Inc.
Author-email: developers@pinn.ai
License: MIT
Platform: UNKNOWN
Classifier: Development Status :: 2 - Pre-Alpha
Classifier: Intended Audience :: Developers
Classifier: License :: OSI Approved :: MIT License
Classifier: Topic :: Software Development :: Libraries :: Python Modules
Classifier: Programming Language :: Python :: 3.4
Classifier: Programming Language :: Python :: 3.5
Classifier: Programming Language :: Python :: 3.6
Classifier: Programming Language :: Python :: 3.7
Classifier: Programming Language :: Python :: Implementation :: PyPy
